projen_publishing_tester/__init__.py
projen_publishing_tester/py.typed
projen_publishing_tester/_jsii/__init__.py
projen_publishing_tester/_jsii/projen-publishing-tester@0.0.2.jsii.tgz
projen_publishing_tester-0.0.2.dist-info/LICENSE
projen_publishing_tester-0.0.2.dist-info/METADATA
projen_publishing_tester-0.0.2.dist-info/WHEEL
projen_publishing_tester-0.0.2.dist-info/top_level.txt
projen_publishing_tester-0.0.2.dist-info/RECORD
